README.txt
setup.py
jsontemplate/__init__.py
jsontemplate/_jsontemplate.py
jsontemplate/datadict.py
jsontemplate/datadict_test.py
jsontemplate/formatters.py
jsontemplate/formatters_test.py
jsontemplate/highlight.py
jsontemplate/jsontemplate_unittest.py
jsontemplate.egg-info/PKG-INFO
jsontemplate.egg-info/SOURCES.txt
jsontemplate.egg-info/dependency_links.txt
jsontemplate.egg-info/top_level.txt