Metadata-Version: 1.0
Name: jsontemplate
Version: 0.85b3
Summary: A declarative templating language based on JSON
Home-page: http://json-template.googlecode.com
Author: Andy Chu
Author-email: json-template@googlegroups.com
License: Apache Software License (v2)
Keywords: json template templating jsontemplate
Platform: UNKNOWN
Classifier: Environment :: Web Environment
Classifier: Intended Audience :: Developers
Classifier: License :: OSI Approved :: Apache Software License
Classifier: Operating System :: OS Independent
Classifier: Programming Language :: Python
Classifier: Topic :: Internet :: WWW/HTTP :: Dynamic Content
Classifier: Topic :: Software Development :: Libraries :: Python Modules
Classifier: Topic :: Text Processing :: Markup :: HTML
